zhDateTime/__init__.py
zhDateTime/constants.py
zhDateTime/main.py
zhDateTime/types.py
zhdatetime-2.0.2.1.dist-info/METADATA
zhdatetime-2.0.2.1.dist-info/WHEEL
zhdatetime-2.0.2.1.dist-info/entry_points.txt
zhdatetime-2.0.2.1.dist-info/licenses/LICENSE
zhdatetime-2.0.2.1.dist-info/RECORD
