Metadata-Version: 2.1
Name: zhDateTime
Version: 2.0.2.1
Summary: 中式日期时间库，附带数字汉字化功能。
Keywords: Chinese Calender,zhdate,calender,datetime,date,time
Author: 金羿Eilles
Maintainer-Email: =?utf-8?b?6YeR576/RWlsbGVz?= <EillesWan@outlook.com>
License:                 木兰宽松许可证, 第2版
Classifier: Intended Audience :: Developers
Classifier: Natural Language :: Chinese (Simplified)
Classifier: Programming Language :: Python
Classifier: Programming Language :: Python :: 3
Classifier: License :: OSI Approved :: Mulan Permissive Software License v2 (MulanPSL-2.0)
Classifier: Operating System :: OS Independent
Classifier: Topic :: Software Development :: Libraries
Project-URL: Repository, https://gitee.com/EillesWan/zhDateTime
Project-URL: Issues, https://gitee.com/EillesWan/zhDateTime/issues
Project-URL: Mirror-Repository, https://github.com/EillesWan/zhDateTime
Project-URL: Mirror-Issues, https://github.com/EillesWan/zhDateTime/issues
Requires-Python: <4.0,>=3.8
Provides-Extra: dev
Requires-Dist: twine; extra == "dev"
Requires-Dist: rich; extra == "dev"
